README.rst
setup.cfg
setup.py
bin/entry.py
sagemaker_container_support.egg-info/PKG-INFO
sagemaker_container_support.egg-info/SOURCES.txt
sagemaker_container_support.egg-info/dependency_links.txt
sagemaker_container_support.egg-info/requires.txt
sagemaker_container_support.egg-info/top_level.txt
src/container_support/__init__.py
src/container_support/environment.py
src/container_support/retrying.py
src/container_support/serving.py
src/container_support/training.py
src/container_support/utils.py
src/container_support/wsgi.py
src/container_support/etc/nginx.conf.template
src/container_support/etc/print_gpu_info.py
src/container_support/etc/telegraf.conf
test/test_environment.py
test/test_serving.py
test/test_utils.py