Metadata-Version: 1.1
Name: sagemaker-container-support
Version: 1.1.1
Summary: Open source library for creating containers to run on Amazon SageMaker.
Home-page: https://github.com/aws/sagemaker-container-support/
Author: Amazon Web Services
Author-email: UNKNOWN
License: Apache License 2.0
Platform: UNKNOWN
Classifier: Development Status :: 5 - Production/Stable
Classifier: Intended Audience :: Developers
Classifier: Natural Language :: English
Classifier: License :: OSI Approved :: Apache Software License
Classifier: Programming Language :: Python
Classifier: Programming Language :: Python :: 2.7
Classifier: Programming Language :: Python :: 3.5
